{
  "program": "B.Com (Regular)",
  "year": "3rd Year",
  "semester": "Semester 5",
  "division": "A",
  "students": [
    {
      "rollNo": "1",
      "spdid": "2024002752",
      "name": "AANYA GOPAL CHANDNANI",
      "gender": "Female",
      "category": "General",
      "email": "gopal.chandnani@gmail.com",
      "phone": "9727644400",
      "subject": "STAT",
      "class": "B.Com. Sem-V"
    },
    {
      "rollNo": "2",
      "spdid": "2024002815",
      "name": "AARFA SABIR LADKA",
      "gender": "Female",
      "category": "SEBC",
      "email": "aarfaladka2@gmail.com",
      "phone": "8200544803",
      "subject": "STAT",
      "class": "B.Com. Sem-V"
    },
    {
      "rollNo": "3",
      "spdid": "2024002820",
      "name": "AARTI GANGAJIBHAI MAHESHWARI",
      "gender": "Female",
      "category": "SC",
      "email": "aartimaheshwari852@gmail.com",
      "phone": "9157199678",
      "subject": "STAT",
      "class": "B.Com. Sem-V"
    },
    {
      "rollNo": "4",
      "spdid": "2024002785",
      "name": "AARTI PRAVINBHAI GADHVI",
      "gender": "Female",
      "category": "SEBC",
      "email": "aartigadhvi4@gmail.com",
      "phone": "9328611292",
      "subject": "STAT",
      "class": "B.Com. Sem-V"
    },
    {
      "rollNo": "5",
      "spdid": "2024002755",
      "name": "AASHIAPRAVEEN NAYEEMUDDIN ANSARI",
      "gender": "Female",
      "category": "General",
      "email": "aashiaansari786@gmail.com",
      "phone": "9558506596",
      "subject": "STAT",
      "class": "B.Com. Sem-V"
    },
    {
      "rollNo": "6",
      "spdid": "2024002871",
      "name": "AAYUSHI ASHOKBHAI SATHVARA",
      "gender": "Female",
      "category": "SEBC",
      "email": "aayushisathwara0511@gmail.com",
      "phone": "9537106571",
      "subject": "STAT",
      "class": "B.Com. Sem-V"
    },
    {
      "rollNo": "7",
      "spdid": "2024002888",
      "name": "ADARSH BHUPENDRA TRIPATHI",
      "gender": "Male",
      "category": "General",
      "email": "tripathiadarsh417@gmail.com",
      "phone": "7495820785",
      "subject": "STAT",
      "class": "B.Com. Sem-V"
    },
    {
      "rollNo": "8",
      "spdid": "2024002759",
      "name": "ADITI NAVINBHAI BHANUSHALI",
      "gender": "Female",
      "category": "EWS",
      "email": "bhanushaliaditi15@gmail.com",
      "phone": "8780561286",
      "subject": "STAT",
      "class": "B.Com. Sem-V"
    },
    {
      "rollNo": "9",
      "spdid": "2024002841",
      "name": "ADITYA ANIL PANJWANI",
      "gender": "Male",
      "category": "General",
      "email": "panjwaniaditya0@gmail.com",
      "phone": "9426162350",
      "subject": "STAT",
      "class": "B.Com. Sem-V"
    },
    {
      "rollNo": "10",
      "spdid": "2024002826",
      "name": "AKSHAY SHAMJIBHAI MARAND",
      "gender": "Male",
      "category": "SEBC",
      "email": "akshayahir0364@gmail.com",
      "phone": "6353131237",
      "subject": "STAT",
      "class": "B.Com. Sem-V"
    },
    {
      "rollNo": "11",
      "spdid": "2024002894",
      "name": "ANJALI RAMESHKUMAR VERMA",
      "gender": "Female",
      "category": "General",
      "email": "anjali2401verma@gmail.com",
      "phone": "9586465818",
      "subject": "STAT",
      "class": "B.Com. Sem-V"
    },
    {
      "rollNo": "12",
      "spdid": "2024002875",
      "name": "ANKITA BRIJESH SINGH",
      "gender": "Female",
      "category": "General",
      "email": "gunjans6151499@gmail.com",
      "phone": "9106461778",
      "subject": "STAT",
      "class": "B.Com. Sem-V"
    },
    {
      "rollNo": "13",
      "spdid": "2024002862",
      "name": "ANKITA KHUSHALBHAI RATHOD",
      "gender": "Female",
      "category": "SC",
      "email": "rathodankita284@gmail.com",
      "phone": "9979730944",
      "subject": "STAT",
      "class": "B.Com. Sem-V"
    },
    {
      "rollNo": "14",
      "spdid": "2024002795",
      "name": "ANSHIKA MAHESH HASWANI",
      "gender": "Female",
      "category": "General",
      "email": "nilammaheshhaswani@gmail.com",
      "phone": "8735022375",
      "subject": "STAT",
      "class": "B.Com. Sem-V"
    },
    {
      "rollNo": "15",
      "spdid": "2024002896",
      "name": "ARJUN SANJAYKUMAR VYAS",
      "gender": "Male",
      "category": "General",
      "email": "arjunvyash0417@gmail.com",
      "phone": "9265137382",
      "subject": "STAT",
      "class": "B.Com. Sem-V"
    },
    {
      "rollNo": "16",
      "spdid": "2024002824",
      "name": "ASHA KANJIBHAI MANANI",
      "gender": "Female",
      "category": "SEBC",
      "email": "aashasathwara123@gmail.com",
      "phone": "6352603566",
      "subject": "STAT",
      "class": "B.Com. Sem-V"
    },
    {
      "rollNo": "17",
      "spdid": "2024002764",
      "name": "ASHOKBHAI BHAVABHAI CHAUDHARY",
      "gender": "Male",
      "category": "SEBC",
      "email": "ashokchaudhary2306@gmail.com",
      "phone": "9924631343",
      "subject": "STAT",
      "class": "B.Com. Sem-V"
    },
    {
      "rollNo": "18",
      "spdid": "2024002843",
      "name": "ASMI SANJAYBHAI PARMAR",
      "gender": "Female",
      "category": "SEBC",
      "email": "asmiparmar2210@gmail.com",
      "phone": "9824226542",
      "subject": "STAT",
      "class": "B.Com. Sem-V"
    },
    {
      "rollNo": "19",
      "spdid": "2024002830",
      "name": "ATULYA SUDEEPKUMAR NAIR",
      "gender": "Female",
      "category": "General",
      "email": "sudeep.nair08@gmail.com",
      "phone": "9909720235",
      "subject": "STAT",
      "class": "B.Com. Sem-V"
    },
    {
      "rollNo": "20",
      "spdid": "2024002821",
      "name": "AVANI MANOJBHAI MAHESHWARI",
      "gender": "Female",
      "category": "SC",
      "email": "avanimaheshwari1904@gmail.com",
      "phone": "9586099528",
      "subject": "STAT",
      "class": "B.Com. Sem-V"
    },
    {
      "rollNo": "21",
      "spdid": "2024002883",
      "name": "AYASHA HUSEN SUMRA",
      "gender": "Female",
      "category": "SEBC",
      "email": "husensumra506@gmail.com",
      "phone": "9898306518",
      "subject": "STAT",
      "class": "B.Com. Sem-V"
    },
    {
      "rollNo": "22",
      "spdid": "2024002802",
      "name": "AYUSHI VILASHKUMAR JETHWA",
      "gender": "Female",
      "category": "SEBC",
      "email": "jethwavilash0@gmail.com",
      "phone": "9714512379",
      "subject": "STAT",
      "class": "B.Com. Sem-V"
    },
    {
      "rollNo": "23",
      "spdid": "2024002819",
      "name": "BALRAM LAKHUBHAI MAHESHVARI",
      "gender": "Male",
      "category": "SC",
      "email": "balrammaheshwari81@gmail.com",
      "phone": "8780093375",
      "subject": "STAT",
      "class": "B.Com. Sem-V"
    },
    {
      "rollNo": "24",
      "spdid": "2024002844",
      "name": "BHAGIRATHSINH HITENDRASINH PARMAR",
      "gender": "Male",
      "category": "EWS",
      "email": "bhagirathsinhparmar2872@gmail.com",
      "phone": "9328762148",
      "subject": "STAT",
      "class": "B.Com. Sem-V"
    },
    {
      "rollNo": "25",
      "spdid": "2024002783",
      "name": "BHARAT RAVI DORU",
      "gender": "Male",
      "category": "General",
      "email": "ravimistry877@gmail.com",
      "phone": "9106530814",
      "subject": "STAT",
      "class": "B.Com. Sem-V"
    },
    {
      "rollNo": "26",
      "spdid": "2024002772",
      "name": "BHARTI PANNASINGH CHOUHAN",
      "gender": "Female",
      "category": "General",
      "email": "singhbhavesh284@gmail.com",
      "phone": "7041965304",
      "subject": "STAT",
      "class": "B.Com. Sem-V"
    },
    {
      "rollNo": "27",
      "spdid": "2024002768",
      "name": "BHAUTIK BHAVESHBHAI CHAVDA",
      "gender": "Male",
      "category": "SEBC",
      "email": "bhautikchavda510@gmail.com",
      "phone": "6355616033",
      "subject": "STAT",
      "class": "B.Com. Sem-V"
    },
    {
      "rollNo": "28",
      "spdid": "2024002845",
      "name": "BHAUTIK MOHANBHAI PARMAR",
      "gender": "Male",
      "category": "SC",
      "email": "parmarbhautik3041987@gmail.com",
      "phone": "8758889846",
      "subject": "STAT",
      "class": "B.Com. Sem-V"
    },
    {
      "rollNo": "29",
      "spdid": "2024002825",
      "name": "BHAVNA NANIK MANGTANI",
      "gender": "Female",
      "category": "EWS",
      "email": "mangtanibhavna6@gmail.com",
      "phone": "8980483720",
      "subject": "STAT",
      "class": "B.Com. Sem-V"
    },
    {
      "rollNo": "30",
      "spdid": "2024002831",
      "name": "BHAVYANATH BHAVESHNATH NATHBAVA",
      "gender": "Male",
      "category": "SEBC",
      "email": "bhavyanath4@gmail.com",
      "phone": "9726731807",
      "subject": "STAT",
      "class": "B.Com. Sem-V"
    },
    {
      "rollNo": "31",
      "spdid": "2024002791",
      "name": "BHOOMI ASHVINBHAI HADIYA",
      "gender": "Female",
      "category": "SEBC",
      "email": "jayshree1234hadiya@gmail.com",
      "phone": "9725083685",
      "subject": "STAT",
      "class": "B.Com. Sem-V"
    },
    {
      "rollNo": "32",
      "spdid": "2024002852",
      "name": "BHOOMI KETANBHAI PITHADIYA",
      "gender": "Female",
      "category": "SEBC",
      "email": "bhoomikpithadiya2411@gmail.com",
      "phone": "8980830787",
      "subject": "STAT",
      "class": "B.Com. Sem-V"
    },
    {
      "rollNo": "33",
      "spdid": "2024002778",
      "name": "BHOOMI VIJAYBHAI DEVALIYA",
      "gender": "Female",
      "category": "SEBC",
      "email": "krishandevaliya@gmail.com",
      "phone": "9924166384",
      "subject": "STAT",
      "class": "B.Com. Sem-V"
    },
    {
      "rollNo": "34",
      "spdid": "2024002816",
      "name": "BHOOMIKA MUKESH LALWANI",
      "gender": "Female",
      "category": "General",
      "email": "bhavikalalwani2002@gmail.com",
      "phone": "8735869342",
      "subject": "STAT",
      "class": "B.Com. Sem-V"
    },
    {
      "rollNo": "35",
      "spdid": "2024002895",
      "name": "BHUMIKA SANTOSH VERMA",
      "gender": "Female",
      "category": "General",
      "email": "bhumikaverma545@gmail.com",
      "phone": "8849751809",
      "subject": "STAT",
      "class": "B.Com. Sem-V"
    },
    {
      "rollNo": "36",
      "spdid": "2024002789",
      "name": "BINDIYA DHAMABHAI GUJARIYA",
      "gender": "Female",
      "category": "SEBC",
      "email": "ahirdeepa07@gmail.com",
      "phone": "9879547537",
      "subject": "STAT",
      "class": "B.Com. Sem-V"
    },
    {
      "rollNo": "37",
      "spdid": "2024002898",
      "name": "BRIJRAJSINH JUVANSINH ZALA",
      "gender": "Male",
      "category": "General",
      "email": "brijrajsinhzala088@gmail.com",
      "phone": "9879517256",
      "subject": "STAT",
      "class": "B.Com. Sem-V"
    },
    {
      "rollNo": "38",
      "spdid": "2024002832",
      "name": "CHIRAG CHANDURAM NAVRANGANI",
      "gender": "Male",
      "category": "EWS",
      "email": "chiragnavrangani@gmail.com",
      "phone": "9998875685",
      "subject": "STAT",
      "class": "B.Com. Sem-V"
    },
    {
      "rollNo": "39",
      "spdid": "2024002839",
      "name": "DARSHAN KAUSHIK PALAN",
      "gender": "Male",
      "category": "General",
      "email": "palandarshan13@gmail.com",
      "phone": "9537026012",
      "subject": "STAT",
      "class": "B.Com. Sem-V"
    },
    {
      "rollNo": "40",
      "spdid": "2024002838",
      "name": "DARSHAN NANAK PADWANI",
      "gender": "Male",
      "category": "General",
      "email": "darshanpadwani61@gmail.com",
      "phone": "9601403616",
      "subject": "STAT",
      "class": "B.Com. Sem-V"
    },
    {
      "rollNo": "41",
      "spdid": "2024002770",
      "name": "DEEP ROHITBHAI CHHATRE",
      "gender": "Male",
      "category": "General",
      "email": "chhatredeep@gmail.com",
      "phone": "9106014597",
      "subject": "STAT",
      "class": "B.Com. Sem-V"
    },
    {
      "rollNo": "42",
      "spdid": "2024002788",
      "name": "DEEPTI SURESH GIDWANI",
      "gender": "Female",
      "category": "General",
      "email": "deeptigidwani0406@gmail.com",
      "phone": "9825114989",
      "subject": "STAT",
      "class": "B.Com. Sem-V"
    },
    {
      "rollNo": "43",
      "spdid": "2024002886",
      "name": "DEV MAHESHBHAI THACKER",
      "gender": "Male",
      "category": "General",
      "email": "thackerdev32@gmail.com",
      "phone": "9016246121",
      "subject": "STAT",
      "class": "B.Com. Sem-V"
    },
    {
      "rollNo": "44",
      "spdid": "2024002771",
      "name": "DEV ROHITBHAI CHHATRE",
      "gender": "Male",
      "category": "General",
      "email": "chhatredev16@gmail.com",
      "phone": "7016152135",
      "subject": "STAT",
      "class": "B.Com. Sem-V"
    },
    {
      "rollNo": "45",
      "spdid": "2024002760",
      "name": "DHARA JAGDISH BHANUSHALI",
      "gender": "Female",
      "category": "General",
      "email": "BHANUSHALIDHARA05@GMAIL.COM",
      "phone": "6352803521",
      "subject": "STAT",
      "class": "B.Com. Sem-V"
    },
    {
      "rollNo": "46",
      "spdid": "2024002773",
      "name": "DHARMAPAL DHIRAJBHAI DAMOR",
      "gender": "Male",
      "category": "ST",
      "email": "dharmapaldamor29@gmail.com",
      "phone": "8758605598",
      "subject": "STAT",
      "class": "B.Com. Sem-V"
    },
    {
      "rollNo": "47",
      "spdid": "2024002877",
      "name": "DHARMESH DHANIBEN SOLANKI",
      "gender": "Male",
      "category": "SC",
      "email": "dharmeshop9898@gmail.com",
      "phone": "9662478212",
      "subject": "STAT",
      "class": "B.Com. Sem-V"
    },
    {
      "rollNo": "48",
      "spdid": "2024002757",
      "name": "DHRUVI JAGDISHBHAI BAMBHANIYA",
      "gender": "Female",
      "category": "SEBC",
      "email": "divaribenbambhaniya@gmail.com",
      "phone": "7567130754",
      "subject": "STAT",
      "class": "B.Com. Sem-V"
    },
    {
      "rollNo": "49",
      "spdid": "2024002899",
      "name": "DHRUVI KANJIBHAI ZARU",
      "gender": "Female",
      "category": "SEBC",
      "email": "dhruviahir9991@gmail.com",
      "phone": "9328605884",
      "subject": "STAT",
      "class": "B.Com. Sem-V"
    },
    {
      "rollNo": "50",
      "spdid": "2024002786",
      "name": "DHRUVI KIRITDAN GADHVI",
      "gender": "Female",
      "category": "SEBC",
      "email": "dhruvi.rohadiya@gmail.com",
      "phone": "9664400103",
      "subject": "STAT",
      "class": "B.Com. Sem-V"
    },
    {
      "rollNo": "51",
      "spdid": "2024002854",
      "name": "DHWANI PREMJI PRAJAPATI",
      "gender": "Female",
      "category": "SEBC",
      "email": "dhwaniprajapati67@gmail.com",
      "phone": "8160269937",
      "subject": "STAT",
      "class": "B.Com. Sem-V"
    },
    {
      "rollNo": "52",
      "spdid": "2024002758",
      "name": "DIMPALBEN HASMUKHBHAI BAROT",
      "gender": "Female",
      "category": "SC",
      "email": "hasmukh.barot83@gmail.com",
      "phone": "9978858698",
      "subject": "STAT",
      "class": "B.Com. Sem-V"
    },
    {
      "rollNo": "53",
      "spdid": "2024002763",
      "name": "DIMPLE BHARAT CHARAN",
      "gender": "Female",
      "category": "SC",
      "email": "dimplecharan329@gmail.com",
      "phone": "8141009281",
      "subject": "STAT",
      "class": "B.Com. Sem-V"
    },
    {
      "rollNo": "54",
      "spdid": "2024002792",
      "name": "DINESHKUMAR DAMJIBHAI HADIYA",
      "gender": "Male",
      "category": "SEBC",
      "email": "dineahahir6@gmail.com",
      "phone": "8849334531",
      "subject": "STAT",
      "class": "B.Com. Sem-V"
    },
    {
      "rollNo": "55",
      "spdid": "2024002775",
      "name": "DISHA BAKULBHAI DARJI",
      "gender": "Female",
      "category": "SEBC",
      "email": "dishadarji241@gmail.com",
      "phone": "9099679190",
      "subject": "STAT",
      "class": "B.Com. Sem-V"
    },
    {
      "rollNo": "56",
      "spdid": "2024002790",
      "name": "DISHA DIPAKGAR GUSAI",
      "gender": "Female",
      "category": "SEBC",
      "email": "dishagusai09@gmail.com",
      "phone": "8758684103",
      "subject": "STAT",
      "class": "B.Com. Sem-V"
    },
    {
      "rollNo": "57",
      "spdid": "2024002765",
      "name": "DISHABA CHANDRASINH CHAUHAN",
      "gender": "Female",
      "category": "EWS",
      "email": "dishachauhan0222@gmail.com",
      "phone": "8980922625",
      "subject": "STAT",
      "class": "B.Com. Sem-V"
    },
    {
      "rollNo": "58",
      "spdid": "2024002846",
      "name": "DITYA PRATAPBHAI PARMAR",
      "gender": "Female",
      "category": "SEBC",
      "email": "dityaparmar35@gmail.com",
      "phone": "8460775653",
      "subject": "STAT",
      "class": "B.Com. Sem-V"
    },
    {
      "rollNo": "59",
      "spdid": "2024002855",
      "name": "DIVAN NAGJIBHAI PRAJAPATI",
      "gender": "Male",
      "category": "SEBC",
      "email": "prajapatidivan119@gmail.com",
      "phone": "9586260232",
      "subject": "STAT",
      "class": "B.Com. Sem-V"
    },
    {
      "rollNo": "60",
      "spdid": "2024002812",
      "name": "DIVYA PRAKASH KEWLANI",
      "gender": "Female",
      "category": "General",
      "email": "divyakewlani67@gmail.com",
      "phone": "9099682765",
      "subject": "STAT",
      "class": "B.Com. Sem-V"
    },
    {
      "rollNo": "61",
      "spdid": "2024002840",
      "name": "DIVYA SANJEEVAN PANJIYAR",
      "gender": "Female",
      "category": "General",
      "email": "panjiyardivya2@gmail.com",
      "phone": "9426163162",
      "subject": "STAT",
      "class": "B.Com. Sem-V"
    },
    {
      "rollNo": "62",
      "spdid": "2024002878",
      "name": "DIVYABA MAHENDRASINH SOLANKI",
      "gender": "Female",
      "category": "SEBC",
      "email": "solankirudrarajsinh3424@gmail.com",
      "phone": "9825021331",
      "subject": "STAT",
      "class": "B.Com. Sem-V"
    },
    {
      "rollNo": "63",
      "spdid": "2024002853",
      "name": "DIYA BIRJUBHAI POMAL",
      "gender": "Female",
      "category": "General",
      "email": "pomaldiya302@gmail.com",
      "phone": "6351845253",
      "subject": "STAT",
      "class": "B.Com. Sem-V"
    },
    {
      "rollNo": "64",
      "spdid": "2024002865",
      "name": "DIYA JIGNESH RAVAL",
      "gender": "Female",
      "category": "General",
      "email": "jiganjar.1979@gmail.com",
      "phone": "9313049881",
      "subject": "STAT",
      "class": "B.Com. Sem-V"
    },
    {
      "rollNo": "65",
      "spdid": "2024002809",
      "name": "DIYA MOHANBHAI KATARIYA",
      "gender": "Female",
      "category": "SEBC",
      "email": "katriyadiya@gmail.com",
      "phone": "9724600560",
      "subject": "STAT",
      "class": "B.Com. Sem-V"
    },
    {
      "rollNo": "66",
      "spdid": "2024002847",
      "name": "DIYA NARESHBHAI PARMAR",
      "gender": "Female",
      "category": "SEBC",
      "email": "parmaralpa133@gmail.com",
      "phone": "9978206578",
      "subject": "STAT",
      "class": "B.Com. Sem-V"
    },
    {
      "rollNo": "67",
      "spdid": "2024002893",
      "name": "ESHA HITESHBHAI VASOYA",
      "gender": "Female",
      "category": "EWS",
      "email": "isha73088@gmail.com",
      "phone": "7359978117",
      "subject": "STAT",
      "class": "B.Com. Sem-V"
    },
    {
      "rollNo": "68",
      "spdid": "2024002766",
      "name": "GANGA JAYANTIBHAI CHAUHAN",
      "gender": "Female",
      "category": "SC",
      "email": "chauhandhan8@gmail.com",
      "phone": "8758607115",
      "subject": "STAT",
      "class": "B.Com. Sem-V"
    },
    {
      "rollNo": "69",
      "spdid": "2024003444",
      "name": "GAURAV MUKESH PATEL",
      "gender": "Male",
      "category": "General",
      "email": "gauravpatel1751@gmail.com",
      "phone": "9558958951",
      "subject": "STAT",
      "class": "B.Com. Sem-V"
    },
    {
      "rollNo": "70",
      "spdid": "2024002892",
      "name": "GAURIBEN KESHAVJIBHAI VANIYA",
      "gender": "Female",
      "category": "SEBC",
      "email": "gaurivaniya364@gmail.com",
      "phone": "9316322383",
      "subject": "STAT",
      "class": "B.Com. Sem-V"
    },
    {
      "rollNo": "71",
      "spdid": "2024002866",
      "name": "GRISITA KAMLESHBHAI RAVAL",
      "gender": "Female",
      "category": "EWS",
      "email": "grisitaraval@gmail.com",
      "phone": "7600475972",
      "subject": "STAT",
      "class": "B.Com. Sem-V"
    },
    {
      "rollNo": "72",
      "spdid": "2024002884",
      "name": "HANISHA VIJAY TEJWANI",
      "gender": "Female",
      "category": "General",
      "email": "vijaytejwani09@gmail.com",
      "phone": "8141282006",
      "subject": "STAT",
      "class": "B.Com. Sem-V"
    },
    {
      "rollNo": "73",
      "spdid": "2024002827",
      "name": "HARDIK MADEVABHAI MATA",
      "gender": "Male",
      "category": "SEBC",
      "email": "madevamata736@gmail.com",
      "phone": "9913442368",
      "subject": "STAT",
      "class": "B.Com. Sem-V"
    },
    {
      "rollNo": "74",
      "spdid": "2024002799",
      "name": "HARDIKSINH SAHADEVSINH JADEJA",
      "gender": "Male",
      "category": "EWS",
      "email": "jadejahardiksinh331@gmail.com",
      "phone": "9106986822",
      "subject": "STAT",
      "class": "B.Com. Sem-V"
    },
    {
      "rollNo": "75",
      "spdid": "2024002756",
      "name": "HARI SHANTILAL BAKUTRA",
      "gender": "Male",
      "category": "SEBC",
      "email": "hariahir8414@gmail.com",
      "phone": "8160229160",
      "subject": "STAT",
      "class": "B.Com. Sem-V"
    },
    {
      "rollNo": "76",
      "spdid": "2024002880",
      "name": "HARSH DILIP SONI",
      "gender": "Male",
      "category": "General",
      "email": "harshdsoni188@gmail.com",
      "phone": "9510076177",
      "subject": "STAT",
      "class": "B.Com. Sem-V"
    },
    {
      "rollNo": "77",
      "spdid": "2024002856",
      "name": "HARSHITA KISHOR PURSWANI",
      "gender": "Female",
      "category": "General",
      "email": "harshitapurswani14@gmail.com",
      "phone": "7600709889",
      "subject": "STAT",
      "class": "B.Com. Sem-V"
    },
    {
      "rollNo": "78",
      "spdid": "2024002787",
      "name": "HASTI NILESHBHAI GANDHI",
      "gender": "Female",
      "category": "General",
      "email": "hastigandhi24@gmail.com",
      "phone": "9327519830",
      "subject": "STAT",
      "class": "B.Com. Sem-V"
    },
    {
      "rollNo": "79",
      "spdid": "2024002885",
      "name": "HEER SUNIL TEWANI",
      "gender": "Female",
      "category": "General",
      "email": "mayatewani5@gmail.com",
      "phone": "9023695317",
      "subject": "STAT",
      "class": "B.Com. Sem-V"
    },
    {
      "rollNo": "80",
      "spdid": "2024002872",
      "name": "HEMA RAGHU SHARMA",
      "gender": "Female",
      "category": "General",
      "email": "raghusharma28111@gmail.com",
      "phone": "8923847906",
      "subject": "STAT",
      "class": "B.Com. Sem-V"
    },
    {
      "rollNo": "81",
      "spdid": "2024002774",
      "name": "HEMAL KESHAV DANICHA",
      "gender": "Female",
      "category": "SC",
      "email": "hemaldanicha@gmail.com",
      "phone": "9909434216",
      "subject": "STAT",
      "class": "B.Com. Sem-V"
    },
    {
      "rollNo": "82",
      "spdid": "2024002762",
      "name": "HEMANSHI ATULBHAI BUDHBHATTI",
      "gender": "Female",
      "category": "EWS",
      "email": "pritisoni2309@gmail.com",
      "phone": "9687905500",
      "subject": "STAT",
      "class": "B.Com. Sem-V"
    },
    {
      "rollNo": "83",
      "spdid": "2024002850",
      "name": "HEMKUMAR HARESHKUMAR PATEL",
      "gender": "Male",
      "category": "General",
      "email": "chhabhaiyahem@gmail.com",
      "phone": "8200224821",
      "subject": "STAT",
      "class": "B.Com. Sem-V"
    },
    {
      "rollNo": "84",
      "spdid": "2024002882",
      "name": "HET MOHANBHAI SORATHIYA",
      "gender": "Male",
      "category": "SEBC",
      "email": "hadiyahet.hmh6300@gmail.com",
      "phone": "9023591868",
      "subject": "STAT",
      "class": "B.Com. Sem-V"
    },
    {
      "rollNo": "85",
      "spdid": "2024002761",
      "name": "HET VINOD BHIYANI",
      "gender": "Male",
      "category": "General",
      "email": "hetbhiyani@gmail.com",
      "phone": "7622836109",
      "subject": "STAT",
      "class": "B.Com. Sem-V"
    },
    {
      "rollNo": "86",
      "spdid": "2024002807",
      "name": "HETVI JAYESHKUMAR KAPDI",
      "gender": "Female",
      "category": "SEBC",
      "email": "kapdihetvi454@gmail.com",
      "phone": "9978161761",
      "subject": "STAT",
      "class": "B.Com. Sem-V"
    },
    {
      "rollNo": "87",
      "spdid": "2024002776",
      "name": "HIMANSHU MANOJ DAVDA",
      "gender": "Male",
      "category": "General",
      "email": "himanshudavda2006@gmail.com",
      "phone": "9825709776",
      "subject": "STAT",
      "class": "B.Com. Sem-V"
    },
    {
      "rollNo": "88",
      "spdid": "2024002848",
      "name": "HINABEN PARSOTAMBHAI PARMAR",
      "gender": "Female",
      "category": "SC",
      "email": "premilaparmar01@gmail.com",
      "phone": "8758991302",
      "subject": "STAT",
      "class": "B.Com. Sem-V"
    },
    {
      "rollNo": "89",
      "spdid": "2024002805",
      "name": "HIRAL PRAKASH KAKKAD",
      "gender": "Female",
      "category": "General",
      "email": "pushpakakkad24@gmail.com",
      "phone": "8141471870",
      "subject": "STAT",
      "class": "B.Com. Sem-V"
    },
    {
      "rollNo": "90",
      "spdid": "2024002822",
      "name": "HIREN LALJIBHAI MAHESHWARI",
      "gender": "Male",
      "category": "SC",
      "email": "hirenbadga1706@gmail.com",
      "phone": "8128660774",
      "subject": "STAT",
      "class": "B.Com. Sem-V"
    },
    {
      "rollNo": "91",
      "spdid": "2024002810",
      "name": "HITEN RAJESHBHAI KATARIYA",
      "gender": "Male",
      "category": "SEBC",
      "email": "h8854948@gmail.com",
      "phone": "8469470565",
      "subject": "STAT",
      "class": "B.Com. Sem-V"
    },
    {
      "rollNo": "92",
      "spdid": "2024002808",
      "name": "JAGRUTIBEN CHIMANBHAI KATARA",
      "gender": "Female",
      "category": "ST",
      "email": "katarachiman55@gmail.com",
      "phone": "9909883904",
      "subject": "STAT",
      "class": "B.Com. Sem-V"
    },
    {
      "rollNo": "93",
      "spdid": "2024002881",
      "name": "JAINI NITINBHAI SONI",
      "gender": "Female",
      "category": "EWS",
      "email": "pnsoni17481@gmail.com",
      "phone": "8140262826",
      "subject": "STAT",
      "class": "B.Com. Sem-V"
    },
    {
      "rollNo": "94",
      "spdid": "2024003109",
      "name": "JAINISH BHAVESHGAR GOSWAMI",
      "gender": "Male",
      "category": "SEBC",
      "email": "Bhaveshgoswami186@gmail.com",
      "phone": "9712038678",
      "subject": "STAT",
      "class": "B.Com. Sem-V"
    },
    {
      "rollNo": "95",
      "spdid": "2024002842",
      "name": "JAINISH KAMAL PANJWANI",
      "gender": "Male",
      "category": "General",
      "email": "jenekpanjwani@gmail.com",
      "phone": "9879443301",
      "subject": "STAT",
      "class": "B.Com. Sem-V"
    },
    {
      "rollNo": "96",
      "spdid": "2024002800",
      "name": "JANKI BHIMJI SIJU",
      "gender": "Female",
      "category": "SC",
      "email": "bhimjisiju05@gmail.com",
      "phone": "8866966254",
      "subject": "STAT",
      "class": "B.Com. Sem-V"
    },
    {
      "rollNo": "97",
      "spdid": "2024002873",
      "name": "JANVEE DHANESH SHARMA",
      "gender": "Female",
      "category": "General",
      "email": "sidhu4588@gmail.com",
      "phone": "9638352101",
      "subject": "STAT",
      "class": "B.Com. Sem-V"
    },
    {
      "rollNo": "98",
      "spdid": "2024002863",
      "name": "JANVIBA SHIVUBHA RATHOD",
      "gender": "Female",
      "category": "EWS",
      "email": "rathodshivubha94@gmail.com",
      "phone": "8200915657",
      "subject": "STAT",
      "class": "B.Com. Sem-V"
    },
    {
      "rollNo": "99",
      "spdid": "2024002777",
      "name": "JAY LALIT DETWANI",
      "gender": "Male",
      "category": "General",
      "email": "jaydetwani1234@gmail.com",
      "phone": "7016892678",
      "subject": "STAT",
      "class": "B.Com. Sem-V"
    },
    {
      "rollNo": "100",
      "spdid": "2024002793",
      "name": "JAYMIN BHARATBHAI HADIYA",
      "gender": "Male",
      "category": "SEBC",
      "email": "jayminhadiya530@gmail.com",
      "phone": "9978336050",
      "subject": "STAT",
      "class": "B.Com. Sem-V"
    },
    {
      "rollNo": "101",
      "spdid": "2024002897",
      "name": "JAYPALSINH JAYMALSINH ZALA",
      "gender": "Male",
      "category": "General",
      "email": "jaypalsinhzala214@gmail.com",
      "phone": "8849093680",
      "subject": "STAT",
      "class": "B.Com. Sem-V"
    },
    {
      "rollNo": "102",
      "spdid": "2024002864",
      "name": "JAYRAJSINH NATVARSINH RATHOD",
      "gender": "Male",
      "category": "General",
      "email": "jayrajrathid07@gmail.com",
      "phone": "7874970965",
      "subject": "STAT",
      "class": "B.Com. Sem-V"
    },
    {
      "rollNo": "103",
      "spdid": "2024002879",
      "name": "JAYVEER ANAND SOLANKI",
      "gender": "Male",
      "category": "General",
      "email": "jayveer3106@gmail.com",
      "phone": "9825849345",
      "subject": "STAT",
      "class": "B.Com. Sem-V"
    },
    {
      "rollNo": "104",
      "spdid": "2024002837",
      "name": "JEEL KANTILAL OZA",
      "gender": "Female",
      "category": "SEBC",
      "email": "jeeloza7@gmail.com",
      "phone": "8849124551",
      "subject": "STAT",
      "class": "B.Com. Sem-V"
    },
    {
      "rollNo": "105",
      "spdid": "2024003372",
      "name": "JEET RAMESH MIRANI",
      "gender": "Male",
      "category": "EWS",
      "email": "jeetmirani4433@gmail.com",
      "phone": "9106620313",
      "subject": "STAT",
      "class": "B.Com. Sem-V"
    },
    {
      "rollNo": "106",
      "spdid": "2024002801",
      "name": "JEET RAMESHBHAI JARU",
      "gender": "Male",
      "category": "SEBC",
      "email": "jeetjaru9023@gmail.com",
      "phone": "6351224978",
      "subject": "STAT",
      "class": "B.Com. Sem-V"
    },
    {
      "rollNo": "107",
      "spdid": "2024003357",
      "name": "JIGNA MOHANBHAI MATANG",
      "gender": "Female",
      "category": "SC",
      "email": "rohit.matang2008@gmail.com",
      "phone": "6353761267",
      "subject": "STAT",
      "class": "B.Com. Sem-V"
    },
    {
      "rollNo": "108",
      "spdid": "2024002991",
      "name": "JIGNESH HARISHBHAI CHARAN",
      "gender": "Male",
      "category": "SC",
      "email": "charanjignesh909@gmail.com",
      "phone": "7990994475",
      "subject": "STAT",
      "class": "B.Com. Sem-V"
    },
    {
      "rollNo": "109",
      "spdid": "2024003572",
      "name": "JIGNESHKUMAR JAYANTILAL SATHWARA",
      "gender": "Male",
      "category": "SEBC",
      "email": "jigneshsathwara2006@gmail.com",
      "phone": "9586584211",
      "subject": "STAT",
      "class": "B.Com. Sem-V"
    },
    {
      "rollNo": "110",
      "spdid": "2024003261",
      "name": "JIYA SURESH LALWANI",
      "gender": "Female",
      "category": "General",
      "email": "jiyalalwani3106@gmail.com",
      "phone": "9773179156",
      "subject": "STAT",
      "class": "B.Com. Sem-V"
    },
    {
      "rollNo": "111",
      "spdid": "2024003544",
      "name": "KANNAN SHAILENDRA RATHORE",
      "gender": "Female",
      "category": "General",
      "email": "mahamaya25250@yahoo.com",
      "phone": "9724350460",
      "subject": "STAT",
      "class": "B.Com. Sem-V"
    },
    {
      "rollNo": "112",
      "spdid": "2024003041",
      "name": "KARAN KARSHANBHAI DANGAR",
      "gender": "Male",
      "category": "SEBC",
      "email": "gopalahir8317@gmail.com",
      "phone": "8160175949",
      "subject": "STAT",
      "class": "B.Com. Sem-V"
    },
    {
      "rollNo": "113",
      "spdid": "2024003766",
      "name": "KARMADEEPSINH GIRIRRAJSINH ZALA",
      "gender": "Male",
      "category": "General",
      "email": "zalagirirajsinh47@gmail.com",
      "phone": "9998211437",
      "subject": "STAT",
      "class": "B.Com. Sem-V"
    },
    {
      "rollNo": "114",
      "spdid": "2024003526",
      "name": "KAVITA BHAVESH RANA",
      "gender": "Female",
      "category": "ST",
      "email": "meandyougifts.gim@gmail.com",
      "phone": "7016926983",
      "subject": "STAT",
      "class": "B.Com. Sem-V"
    },
    {
      "rollNo": "115",
      "spdid": "2024003661",
      "name": "KAVITA DINESH SONARIWAL",
      "gender": "Female",
      "category": "General",
      "email": "dinesh.sonarival001@gmail.com",
      "phone": "6359304744",
      "subject": "STAT",
      "class": "B.Com. Sem-V"
    },
    {
      "rollNo": "116",
      "spdid": "2024002964",
      "name": "KAVITA RAMESH BHATI",
      "gender": "Female",
      "category": "General",
      "email": "bhatikavita0110@gmail.com",
      "phone": "9484992671",
      "subject": "STAT",
      "class": "B.Com. Sem-V"
    },
    {
      "rollNo": "117",
      "spdid": "2024003626",
      "name": "KAVYARAJSINH CHANDANSINH SODHA",
      "gender": "Male",
      "category": "EWS",
      "email": "kavyarajsinhsodha@gmail.com",
      "phone": "9825597498",
      "subject": "STAT",
      "class": "B.Com. Sem-V"
    },
    {
      "rollNo": "118",
      "spdid": "2024003620",
      "name": "KESHWARSINGH DAROGASINGH SINGH",
      "gender": "Male",
      "category": "General",
      "email": "keshwarsingh521@gmail.com",
      "phone": "8511567899",
      "subject": "STAT",
      "class": "B.Com. Sem-V"
    },
    {
      "rollNo": "119",
      "spdid": "2024003447",
      "name": "KHUSHALI DINESH PATEL",
      "gender": "Female",
      "category": "SEBC",
      "email": "khushalip86@gmail.com",
      "phone": "7405033270",
      "subject": "STAT",
      "class": "B.Com. Sem-V"
    },
    {
      "rollNo": "120",
      "spdid": "2024003448",
      "name": "KHUSHBU SANDEEP PATEL",
      "gender": "Female",
      "category": "General",
      "email": "sandeeppatel8672@gmail.com",
      "phone": "7990485609",
      "subject": "STAT",
      "class": "B.Com. Sem-V"
    },
    {
      "rollNo": "121",
      "spdid": "2024003706",
      "name": "KHUSHI ANILKUMAR TOMAR",
      "gender": "Female",
      "category": "General",
      "email": "sammi.anil.1433@gmail.com",
      "phone": "7987761270",
      "subject": "STAT",
      "class": "B.Com. Sem-V"
    },
    {
      "rollNo": "122",
      "spdid": "2024002986",
      "name": "KHUSHI HARESH CHANCHLANI",
      "gender": "Female",
      "category": "General",
      "email": "khushichanchlanichanchlani@gmail.com",
      "phone": "9327968851",
      "subject": "STAT",
      "class": "B.Com. Sem-V"
    },
    {
      "rollNo": "123",
      "spdid": "2024003021",
      "name": "KHUSHI HASMUKHBHAI CHHAYA",
      "gender": "Female",
      "category": "General",
      "email": "kp11731@gmail.com",
      "phone": "9687268260",
      "subject": "STAT",
      "class": "B.Com. Sem-V"
    },
    {
      "rollNo": "124",
      "spdid": "2024003557",
      "name": "KHUSHI PRAVIN SAINI",
      "gender": "Female",
      "category": "SEBC",
      "email": "khushipravin.saini@gmail.com",
      "phone": "7990366175",
      "subject": "STAT",
      "class": "B.Com. Sem-V"
    },
    {
      "rollNo": "125",
      "spdid": "2024003131",
      "name": "KHUSHI UMESHGAR GUSAI",
      "gender": "Female",
      "category": "SEBC",
      "email": "gusaikaruna@gmail.com",
      "phone": "7874601975",
      "subject": "STAT",
      "class": "B.Com. Sem-V"
    },
    {
      "rollNo": "126",
      "spdid": "2024003425",
      "name": "KHUSHIBA RAJUBHA PARMAR",
      "gender": "Female",
      "category": "General",
      "email": "parmarrushiraj16@gmail.com",
      "phone": "9979526641",
      "subject": "STAT",
      "class": "B.Com. Sem-V"
    },
    {
      "rollNo": "127",
      "spdid": "2024002931",
      "name": "KINJAL MAHESHBHAI BALDANIYA",
      "gender": "Female",
      "category": "SEBC",
      "email": "rajeshsorathiya201@gmail.com",
      "phone": "9586534201",
      "subject": "STAT",
      "class": "B.Com. Sem-V"
    },
    {
      "rollNo": "128",
      "spdid": "2024003598",
      "name": "KINJALBEN NAVGHANBHAI SHIROYA",
      "gender": "Female",
      "category": "SEBC",
      "email": "harshadshiroya03@gmail.com",
      "phone": "9313272370",
      "subject": "STAT",
      "class": "B.Com. Sem-V"
    },
    {
      "rollNo": "129",
      "spdid": "2024003370",
      "name": "KIRTIBEN DHARMENDRABHAI META",
      "gender": "Female",
      "category": "SEBC",
      "email": "ahirvishnu684@gmail.com",
      "phone": "9909122443",
      "subject": "STAT",
      "class": "B.Com. Sem-V"
    },
    {
      "rollNo": "130",
      "spdid": "2024003508",
      "name": "KISHAN VISHABHAI RABARI",
      "gender": "Male",
      "category": "SEBC",
      "email": "kishurabari27@gmail.com",
      "phone": "8849209742",
      "subject": "STAT",
      "class": "B.Com. Sem-V"
    },
    {
      "rollNo": "131",
      "spdid": "2024003295",
      "name": "KOMAL AATMARAMBHAI MAHESHWARI",
      "gender": "Female",
      "category": "SC",
      "email": "komal.kam2000@gmail.com",
      "phone": "7069363738",
      "subject": "STAT",
      "class": "B.Com. Sem-V"
    },
    {
      "rollNo": "132",
      "spdid": "2024003621",
      "name": "KOMAL BALESHWAR SINGH",
      "gender": "Female",
      "category": "General",
      "email": "prachisingh122003@gmail.com",
      "phone": "9408838270",
      "subject": "STAT",
      "class": "B.Com. Sem-V"
    },
    {
      "rollNo": "133",
      "spdid": "2024003000",
      "name": "KOMAL PREMRAJ CHAUHAN",
      "gender": "Female",
      "category": "General",
      "email": "komal96623@gmail.com",
      "phone": "9662323437",
      "subject": "STAT",
      "class": "B.Com. Sem-V"
    },
    {
      "rollNo": "134",
      "spdid": "2024003645",
      "name": "KOMAL RAMESHBHAI SOLANKI",
      "gender": "Female",
      "category": "SEBC",
      "email": "komalsolanki0612@gmail.com",
      "phone": "8200360397",
      "subject": "STAT",
      "class": "B.Com. Sem-V"
    },
    {
      "rollNo": "135",
      "spdid": "2024003001",
      "name": "KRIPA RAHULBHAI CHAUHAN",
      "gender": "Female",
      "category": "EWS",
      "email": "kripa232005@gmail.com",
      "phone": "8849086138",
      "subject": "STAT",
      "class": "B.Com. Sem-V"
    },
    {
      "rollNo": "136",
      "spdid": "2024003238",
      "name": "KRISHIKA JITENDRA KHATRI",
      "gender": "Female",
      "category": "General",
      "email": "luckykhatri2018@gmail.com",
      "phone": "8141601307",
      "subject": "STAT",
      "class": "B.Com. Sem-V"
    },
    {
      "rollNo": "137",
      "spdid": "2024003043",
      "name": "KRISHNA DINESHBHAI DANGAR",
      "gender": "Female",
      "category": "SEBC",
      "email": "krishnaahir797@gmail.com",
      "phone": "9327453384",
      "subject": "STAT",
      "class": "B.Com. Sem-V"
    },
    {
      "rollNo": "138",
      "spdid": "2024003406",
      "name": "KRISHNA JAYKISAN PAMVANI",
      "gender": "Female",
      "category": "General",
      "email": "pamwanikrishna0@gmail.com",
      "phone": "9313136984",
      "subject": "STAT",
      "class": "B.Com. Sem-V"
    },
    {
      "rollNo": "139",
      "spdid": "2024003268",
      "name": "KRISHNA SHAILESHKUMAR MAAHESHWARI",
      "gender": "Female",
      "category": "EWS",
      "email": "maheshwarij79@gmail.com",
      "phone": "9687192054",
      "subject": "STAT",
      "class": "B.Com. Sem-V"
    },
    {
      "rollNo": "140",
      "spdid": "2024003260",
      "name": "KRISHNA VIJAY LALCHANDANI",
      "gender": "Male",
      "category": "EWS",
      "email": "kvlalchandani2006@gmail.com",
      "phone": "9054180573",
      "subject": "STAT",
      "class": "B.Com. Sem-V"
    },
    {
      "rollNo": "141",
      "spdid": "2024003681",
      "name": "KRUPA ASHOK THACKER",
      "gender": "Female",
      "category": "General",
      "email": "krupathakkar022@gmail.com",
      "phone": "9924074537",
      "subject": "STAT",
      "class": "B.Com. Sem-V"
    },
    {
      "rollNo": "142",
      "spdid": "2024003682",
      "name": "KRUPA HITESHBHAI THACKER",
      "gender": "Female",
      "category": "General",
      "email": "krupathacker080@gmail.com",
      "phone": "9429963582",
      "subject": "STAT",
      "class": "B.Com. Sem-V"
    },
    {
      "rollNo": "143",
      "spdid": "2024003450",
      "name": "KRUPA MANISH PATEL",
      "gender": "Female",
      "category": "General",
      "email": "manishdpatel421@gmail.com",
      "phone": "9879322421",
      "subject": "STAT",
      "class": "B.Com. Sem-V"
    },
    {
      "rollNo": "144",
      "spdid": "2024003343",
      "name": "KRUPALI DIPAKBHAI MANGE",
      "gender": "Female",
      "category": "General",
      "email": "deepakbhanushali304@gmail.com",
      "phone": "9925117087",
      "subject": "STAT",
      "class": "B.Com. Sem-V"
    },
    {
      "rollNo": "145",
      "spdid": "2024003761",
      "name": "KUNAL GANESHCHANDRA YADAV",
      "gender": "Male",
      "category": "SEBC",
      "email": "yaganeshchandra@gmail.com",
      "phone": "8780681734",
      "subject": "STAT",
      "class": "B.Com. Sem-V"
    },
    {
      "rollNo": "146",
      "spdid": "2024003004",
      "name": "MADHAVI ASHVINBHAI CHAUHAN",
      "gender": "Female",
      "category": "SEBC",
      "email": "cmadhavi966@gmail.com",
      "phone": "9106285138",
      "subject": "STAT",
      "class": "B.Com. Sem-V"
    },
    {
      "rollNo": "147",
      "spdid": "2024003683",
      "name": "MAHEK ASHOK THACKER",
      "gender": "Female",
      "category": "General",
      "email": "mahekthacker213@gmail.com",
      "phone": "8200700177",
      "subject": "STAT",
      "class": "B.Com. Sem-V"
    },
    {
      "rollNo": "148",
      "spdid": "2024003439",
      "name": "MAHEK BALARAM PATARIYA",
      "gender": "Female",
      "category": "SC",
      "email": "balaramrm216@gmail.com",
      "phone": "9712136763",
      "subject": "STAT",
      "class": "B.Com. Sem-V"
    },
    {
      "rollNo": "149",
      "spdid": "2024003501",
      "name": "MAHEK RAVINDRABHAI PURABIYA",
      "gender": "Female",
      "category": "SC",
      "email": "ravindra.purabia1@gmail.com",
      "phone": "9106594374",
      "subject": "STAT",
      "class": "B.Com. Sem-V"
    },
    {
      "rollNo": "150",
      "spdid": "2024003272",
      "name": "MAHESH BHIMJIBHAI MAHESHVARI",
      "gender": "Male",
      "category": "SC",
      "email": "vishal.b8944@gmail.com",
      "phone": "7874909761",
      "subject": "STAT",
      "class": "B.Com. Sem-V"
    },
    {
      "rollNo": "151",
      "spdid": "2024003409",
      "name": "MAHESH HITESHBHAI PANCHAL",
      "gender": "Male",
      "category": "SEBC",
      "email": "hiteshbhaipanchal64@gmail.com",
      "phone": "9909759302",
      "subject": "STAT",
      "class": "B.Com. Sem-V"
    },
    {
      "rollNo": "152",
      "spdid": "2024003742",
      "name": "MAHESHBHAI MOHANBHAI VARCHAND",
      "gender": "Male",
      "category": "SEBC",
      "email": "ahir44153@gmail.com",
      "phone": "9624344153",
      "subject": "STAT",
      "class": "B.Com. Sem-V"
    },
    {
      "rollNo": "153",
      "spdid": "2024003524",
      "name": "MAHIMA MAHESH RAMANI",
      "gender": "Female",
      "category": "EWS",
      "email": "mahimaramani781@gmail.com",
      "phone": "8866607917",
      "subject": "STAT",
      "class": "B.Com. Sem-V"
    },
    {
      "rollNo": "154",
      "spdid": "2024003534",
      "name": "MAITRI ARUNBHAI RATHOD",
      "gender": "Female",
      "category": "SEBC",
      "email": "rathodmaitri084@gmail.com",
      "phone": "7984331182",
      "subject": "STAT",
      "class": "B.Com. Sem-V"
    },
    {
      "rollNo": "155",
      "spdid": "2024003093",
      "name": "MAITRI HASMUKHBHAI GANATRA",
      "gender": "Female",
      "category": "EWS",
      "email": "maitri.ganatra2006@gmail.com",
      "phone": "9054417106",
      "subject": "STAT",
      "class": "B.Com. Sem-V"
    },
    {
      "rollNo": "156",
      "spdid": "2024003520",
      "name": "MANDIRA VINODBHAI RAJGOR",
      "gender": "Female",
      "category": "General",
      "email": "rajgormandira7@gmail.com",
      "phone": "9313752376",
      "subject": "STAT",
      "class": "B.Com. Sem-V"
    },
    {
      "rollNo": "157",
      "spdid": "2024003590",
      "name": "MANJEETKUMAR ANIL SHARMA",
      "gender": "Male",
      "category": "General",
      "email": "man4545jeet@gmail.com",
      "phone": "8733890865",
      "subject": "STAT",
      "class": "B.Com. Sem-V"
    },
    {
      "rollNo": "158",
      "spdid": "2024003581",
      "name": "MANOJ RAJESH SAXENA",
      "gender": "Male",
      "category": "General",
      "email": "saxenamanoj206@gmail.com",
      "phone": "9664587990",
      "subject": "STAT",
      "class": "B.Com. Sem-V"
    },
    {
      "rollNo": "159",
      "spdid": "2024003113",
      "name": "MANSI DAYARAM GOYAL",
      "gender": "Female",
      "category": "General",
      "email": "dayaramgoyal484@gmail.com",
      "phone": "9978343265",
      "subject": "STAT",
      "class": "B.Com. Sem-V"
    },
    {
      "rollNo": "160",
      "spdid": "2024003411",
      "name": "MANSI MANISHBHAI PANDYA",
      "gender": "Female",
      "category": "General",
      "email": "manishpandya719@gmail.com",
      "phone": "9825504705",
      "subject": "STAT",
      "class": "B.Com. Sem-V"
    },
    {
      "rollNo": "161",
      "spdid": "2024003114",
      "name": "MANSI PUKHRAJ GOYAL",
      "gender": "Female",
      "category": "General",
      "email": "mansigoyalmansigoyal@gmail.com",
      "phone": "7405958713",
      "subject": "STAT",
      "class": "B.Com. Sem-V"
    },
    {
      "rollNo": "162",
      "spdid": "2024003428",
      "name": "MANTHAN MAHESHBHAI PARMAR",
      "gender": "Male",
      "category": "SEBC",
      "email": "parmarmanthan689@gmail.com",
      "phone": "9157682250",
      "subject": "STAT",
      "class": "B.Com. Sem-V"
    },
    {
      "rollNo": "163",
      "spdid": "2024003599",
      "name": "MANTHAN MANISHBHAI SHIYALWALA",
      "gender": "Male",
      "category": "SEBC",
      "email": "manishkharva2577@gmail.com",
      "phone": "7383623668",
      "subject": "STAT",
      "class": "B.Com. Sem-V"
    },
    {
      "rollNo": "164",
      "spdid": "2024003764",
      "name": "MAYANK SUNDARBHAI ZAA",
      "gender": "Male",
      "category": "General",
      "email": "mayank19416@gmail.com",
      "phone": "9104839294",
      "subject": "STAT",
      "class": "B.Com. Sem-V"
    },
    {
      "rollNo": "165",
      "spdid": "2024003217",
      "name": "MAYUR BHARATBHAI KAPDI",
      "gender": "Male",
      "category": "SEBC",
      "email": "mayurkapdi15@gmail.com",
      "phone": "9824457746",
      "subject": "STAT",
      "class": "B.Com. Sem-V"
    },
    {
      "rollNo": "166",
      "spdid": "2024003387",
      "name": "MAYURI PARBATBHAI NAI",
      "gender": "Female",
      "category": "SEBC",
      "email": "naipravin808@gmail.com",
      "phone": "8141660993",
      "subject": "STAT",
      "class": "B.Com. Sem-V"
    },
    {
      "rollNo": "167",
      "spdid": "2024003438",
      "name": "MEET AMRISHBHAI PATADIYA",
      "gender": "Male",
      "category": "EWS",
      "email": "soniamrish02@gmail.com",
      "phone": "8460157860",
      "subject": "STAT",
      "class": "B.Com. Sem-V"
    },
    {
      "rollNo": "168",
      "spdid": "2024002955",
      "name": "MEET RAJESH BHANUSHALI",
      "gender": "Male",
      "category": "EWS",
      "email": "meetbhanusali96@gmail.com",
      "phone": "9067059122",
      "subject": "STAT",
      "class": "B.Com. Sem-V"
    },
    {
      "rollNo": "169",
      "spdid": "2024003743",
      "name": "MEET RAMESHBHAI VARCHAND",
      "gender": "Male",
      "category": "SEBC",
      "email": "varchandmeet97@gmail.com",
      "phone": "7984227912",
      "subject": "STAT",
      "class": "B.Com. Sem-V"
    },
    {
      "rollNo": "170",
      "spdid": "2024002984",
      "name": "MIHIR MOHANBHAI CHAD",
      "gender": "Male",
      "category": "SEBC",
      "email": "mihirahir9391@gmail.com",
      "phone": "9510789172",
      "subject": "STAT",
      "class": "B.Com. Sem-V"
    },
    {
      "rollNo": "171",
      "spdid": "2024003441",
      "name": "MITAL BALARAM PATARIYA",
      "gender": "Female",
      "category": "SC",
      "email": "balaramrm12345@gmail.com",
      "phone": "9979719863",
      "subject": "STAT",
      "class": "B.Com. Sem-V"
    },
    {
      "rollNo": "172",
      "spdid": "2024003594",
      "name": "MOHAMMAD SOHIL IBRAHIMALI SHEKH",
      "gender": "Male",
      "category": "General",
      "email": "shekhsohil1910@gmail.com",
      "phone": "7778828970",
      "subject": "STAT",
      "class": "B.Com. Sem-V"
    },
    {
      "rollNo": "173",
      "spdid": "2024003239",
      "name": "MOHMAD TAHIR ABDULKADAR KHATRI",
      "gender": "Male",
      "category": "General",
      "email": "tahirkhatri619@gmail.com",
      "phone": "8200698834",
      "subject": "STAT",
      "class": "B.Com. Sem-V"
    },
    {
      "rollNo": "174",
      "spdid": "2024002925",
      "name": "MUNNI RAMESHBHAI BABARIYA",
      "gender": "Female",
      "category": "SEBC",
      "email": "shivaniahir531@gmail.com",
      "phone": "9925744617",
      "subject": "STAT",
      "class": "B.Com. Sem-V"
    },
    {
      "rollNo": "175",
      "spdid": "2024003591",
      "name": "MUSKAN ASHOK SHARMA",
      "gender": "Female",
      "category": "General",
      "email": "sharmamuskan6907@gmail.com",
      "phone": "9054377602",
      "subject": "STAT",
      "class": "B.Com. Sem-V"
    },
    {
      "rollNo": "176",
      "spdid": "2024003147",
      "name": "NANDANI HARESH HEMANI",
      "gender": "Female",
      "category": "General",
      "email": "nandanibhanushali2@gmail.com",
      "phone": "7600892608",
      "subject": "STAT",
      "class": "B.Com. Sem-V"
    },
    {
      "rollNo": "177",
      "spdid": "2024003554",
      "name": "NANDANI JANKIDAS SADHU",
      "gender": "Female",
      "category": "SEBC",
      "email": "parthsadhu989@gmail.com",
      "phone": "9687517924",
      "subject": "STAT",
      "class": "B.Com. Sem-V"
    },
    {
      "rollNo": "178",
      "spdid": "2024003704",
      "name": "NANDANI MANOJ TIRTHANI",
      "gender": "Female",
      "category": "General",
      "email": "nandanitirthani5@gmail.com",
      "phone": "8200697905",
      "subject": "STAT",
      "class": "B.Com. Sem-V"
    },
    {
      "rollNo": "179",
      "spdid": "2024003083",
      "name": "NANDANI SURESHBHAI GADHVI",
      "gender": "Female",
      "category": "SEBC",
      "email": "sureshgadhavi1870@gmail.com",
      "phone": "9879714421",
      "subject": "STAT",
      "class": "B.Com. Sem-V"
    },
    {
      "rollNo": "180",
      "spdid": "2024003646",
      "name": "NANDNI KHETSHIBHAI SOLANKI",
      "gender": "Female",
      "category": "SEBC",
      "email": "malinandani517@gmail.com",
      "phone": "9313774623",
      "subject": "STAT",
      "class": "B.Com. Sem-V"
    },
    {
      "rollNo": "181",
      "spdid": "2024003502",
      "name": "NEET BHARGAV PUROHIT",
      "gender": "Male",
      "category": "General",
      "email": "neetpurohit0@gmail.com",
      "phone": "8758184662",
      "subject": "STAT",
      "class": "B.Com. Sem-V"
    },
    {
      "rollNo": "182",
      "spdid": "2024003574",
      "name": "NEHAL SURESHBHAI SATHWARA",
      "gender": "Female",
      "category": "SEBC",
      "email": "nehalsathwara2006@gmail.com",
      "phone": "9978008091",
      "subject": "STAT",
      "class": "B.Com. Sem-V"
    },
    {
      "rollNo": "183",
      "spdid": "2024003627",
      "name": "NETALBA HINDUSINH SODHA",
      "gender": "Female",
      "category": "General",
      "email": "hindusinghs63@gmail.com",
      "phone": "8160952785",
      "subject": "STAT",
      "class": "B.Com. Sem-V"
    },
    {
      "rollNo": "184",
      "spdid": "2024003647",
      "name": "NIDHI MANISH SOLANKI",
      "gender": "Female",
      "category": "SEBC",
      "email": "vs4466109@gmail.com",
      "phone": "9998640045",
      "subject": "STAT",
      "class": "B.Com. Sem-V"
    },
    {
      "rollNo": "185",
      "spdid": "2024002932",
      "name": "NIDHI PRAVINBHAI BALDANIYA",
      "gender": "Female",
      "category": "SEBC",
      "email": "nidhisorthiya11@gmail.com",
      "phone": "9173879312",
      "subject": "STAT",
      "class": "B.Com. Sem-V"
    },
    {
      "rollNo": "186",
      "spdid": "2024003203",
      "name": "NIDHI RAMESH JOGANI",
      "gender": "Female",
      "category": "SEBC",
      "email": "njogani2102@gmail.com",
      "phone": "7016477088",
      "subject": "STAT",
      "class": "B.Com. Sem-V"
    },
    {
      "rollNo": "187",
      "spdid": "2024003174",
      "name": "NIDHIBA ANIRUDHSINH JADEJA",
      "gender": "Female",
      "category": "General",
      "email": "avjadeja@yahoo.com",
      "phone": "9909226300",
      "subject": "STAT",
      "class": "B.Com. Sem-V"
    },
    {
      "rollNo": "188",
      "spdid": "2024003243",
      "name": "NIHAL MANJI KHOKHAR",
      "gender": "Male",
      "category": "SC",
      "email": "nihalk0109@gmail.com",
      "phone": "9429811901",
      "subject": "STAT",
      "class": "B.Com. Sem-V"
    },
    {
      "rollNo": "189",
      "spdid": "2024003566",
      "name": "NIRAL MUKESHBHAI SATHAWARA",
      "gender": "Female",
      "category": "SEBC",
      "email": "damyntisathwara@gmail.com",
      "phone": "9712482708",
      "subject": "STAT",
      "class": "B.Com. Sem-V"
    },
    {
      "rollNo": "190",
      "spdid": "2024003575",
      "name": "NIRALI HARESHBHAI SATHWARA",
      "gender": "Female",
      "category": "SEBC",
      "email": "hiteshsathwara1204@gmail.com",
      "phone": "9726458830",
      "subject": "STAT",
      "class": "B.Com. Sem-V"
    },
    {
      "rollNo": "191",
      "spdid": "2024003116",
      "name": "NIRAV BHAVESH GUJARIYA",
      "gender": "Male",
      "category": "SEBC",
      "email": "niravahir320@gmail.com",
      "phone": "7043102314",
      "subject": "STAT",
      "class": "B.Com. Sem-V"
    },
    {
      "rollNo": "192",
      "spdid": "2024003478",
      "name": "NISHA NAVINBHAI PRAJAPATI",
      "gender": "Female",
      "category": "SEBC",
      "email": "nishaprajapati250707@gmail.com",
      "phone": "9824751087",
      "subject": "STAT",
      "class": "B.Com. Sem-V"
    },
    {
      "rollNo": "193",
      "spdid": "2024003099",
      "name": "NISHA RAJESHBHAI GEDIYA",
      "gender": "Female",
      "category": "SEBC",
      "email": "gediyashivangi11223@gmail.com",
      "phone": "9313396686",
      "subject": "STAT",
      "class": "B.Com. Sem-V"
    },
    {
      "rollNo": "194",
      "spdid": "2024003301",
      "name": "NITESH DHANJI MAHESHWARI",
      "gender": "Male",
      "category": "SC",
      "email": "niteshmaheshwari825@gmail.com",
      "phone": "9327097756",
      "subject": "STAT",
      "class": "B.Com. Sem-V"
    },
    {
      "rollNo": "195",
      "spdid": "2024003555",
      "name": "NITESH JAYANTIBHAI SAGATHIYA",
      "gender": "Male",
      "category": "SC",
      "email": "sagathiyaniteshsagathiya@gmail.com",
      "phone": "7990404977",
      "subject": "STAT",
      "class": "B.Com. Sem-V"
    },
    {
      "rollNo": "196",
      "spdid": "2024003015",
      "name": "NIYATI NILESH CHAVDA",
      "gender": "Female",
      "category": "SEBC",
      "email": "niyatichavda9tha@gmail.com",
      "phone": "8799613857",
      "subject": "STAT",
      "class": "B.Com. Sem-V"
    },
    {
      "rollNo": "197",
      "spdid": "2024003006",
      "name": "OM PRAVINBHAI CHAUHAN",
      "gender": "Male",
      "category": "SEBC",
      "email": "ompchauhan2203@gmail.com",
      "phone": "9898008320",
      "subject": "STAT",
      "class": "B.Com. Sem-V"
    },
    {
      "rollNo": "198",
      "spdid": "2024003089",
      "name": "PALAK HEMANT GAGLANI",
      "gender": "Female",
      "category": "General",
      "email": "chandnigaglani23@gmail.com",
      "phone": "9558506004",
      "subject": "STAT",
      "class": "B.Com. Sem-V"
    },
    {
      "rollNo": "199",
      "spdid": "2024003345",
      "name": "PALAK PANKAJ MANGLANI",
      "gender": "Female",
      "category": "EWS",
      "email": "palakmanglani15@gmail.com",
      "phone": "9662747197",
      "subject": "STAT",
      "class": "B.Com. Sem-V"
    },
    {
      "rollNo": "200",
      "spdid": "2024003454",
      "name": "PARITA KISHORBHAI PATEL",
      "gender": "Female",
      "category": "SEBC",
      "email": "patelparita188@gmail.com",
      "phone": "8320422863",
      "subject": "STAT",
      "class": "B.Com. Sem-V"
    }
  ]
}